{
  "tooljet_database": [],
  "app": [
    {
      "definition": {
        "appV2": {
          "id": "62ee07c7-9d1e-4b9f-bb7b-ee1945dd45a9",
          "type": "front-end",
          "name": "Hintz-template-app",
          "slug": "62ee07c7-9d1e-4b9f-bb7b-ee1945dd45a9",
          "isPublic": null,
          "isMaintenanceOn": false,
          "icon": "draghandle",
          "organizationId": "ad9fffc1-fdd6-4036-be86-ea745954f560",
          "currentVersionId": null,
          "userId": "eccf47b3-2ad4-447f-8016-4b44042ba658",
          "workflowApiToken": null,
          "workflowEnabled": false,
          "createdAt": "2024-08-02T12:27:18.095Z",
          "creationMode": "DEFAULT",
          "updatedAt": "2024-08-02T12:27:18.094Z",
          "editingVersion": {
            "id": "ad863006-8950-4473-b447-7fa667df2ba8",
            "name": "v2",
            "definition": null,
            "globalSettings": {
              "hideHeader": false,
              "appInMaintenance": false,
              "canvasMaxWidth": 100,
              "canvasMaxWidthType": "%",
              "canvasMaxHeight": 2400,
              "canvasBackgroundColor": "#edeff5",
              "backgroundFxQuery": "",
              "appMode": "auto"
            },
            "showViewerNavigation": true,
            "homePageId": "4726e34e-2599-4fc1-9172-b0c2bda7ce68",
            "appId": "62ee07c7-9d1e-4b9f-bb7b-ee1945dd45a9",
            "currentEnvironmentId": "50f55fc8-608e-4bbb-a79f-24306fe81e23",
            "promotedFrom": null,
            "createdAt": "2024-08-02T12:27:34.121Z",
            "updatedAt": "2024-08-02T12:27:34.111Z"
          },
          "components": [
            {
              "id": "4070ac29-80f3-4e33-aad7-73484efdee08",
              "name": "ernie",
              "type": "TextInput",
              "pageId": "4726e34e-2599-4fc1-9172-b0c2bda7ce68",
              "parent": null,
              "properties": {},
              "general": null,
              "styles": {},
              "generalStyles": null,
              "displayPreferences": {
                "showOnDesktop": {
                  "value": "{{true}}"
                },
                "showOnMobile": {
                  "value": "{{false}}"
                }
              },
              "validation": {},
              "createdAt": "2024-08-02T12:27:34.111Z",
              "updatedAt": "2024-08-02T12:27:34.111Z",
              "layouts": [
                {
                  "id": "d3fe868f-acf1-4e81-8d71-e00ae5c47be4",
                  "type": "desktop",
                  "top": 240,
                  "left": 10,
                  "width": 10,
                  "height": 40,
                  "componentId": "4070ac29-80f3-4e33-aad7-73484efdee08",
                  "dimensionUnit": "count",
                  "updatedAt": "2024-08-02T12:27:34.111Z"
                },
                {
                  "id": "7f932f79-216c-4f4d-9bf5-c5113b5f59af",
                  "type": "mobile",
                  "top": 240,
                  "left": 10,
                  "width": 10,
                  "height": 40,
                  "componentId": "4070ac29-80f3-4e33-aad7-73484efdee08",
                  "dimensionUnit": "count",
                  "updatedAt": "2024-08-02T12:27:34.111Z"
                }
              ]
            }
          ],
          "pages": [
            {
              "id": "4726e34e-2599-4fc1-9172-b0c2bda7ce68",
              "name": "Home",
              "handle": "home",
              "index": 1,
              "disabled": null,
              "hidden": null,
              "createdAt": "2024-08-02T12:27:34.111Z",
              "updatedAt": "2024-08-02T12:27:34.111Z",
              "autoComputeLayout": false,
              "appVersionId": "ad863006-8950-4473-b447-7fa667df2ba8"
            }
          ],
          "events": [],
          "dataQueries": [],
          "dataSources": [],
          "appVersions": [
            {
              "id": "ad863006-8950-4473-b447-7fa667df2ba8",
              "name": "v2",
              "definition": null,
              "globalSettings": {
                "hideHeader": false,
                "appInMaintenance": false,
                "canvasMaxWidth": 100,
                "canvasMaxWidthType": "%",
                "canvasMaxHeight": 2400,
                "canvasBackgroundColor": "#edeff5",
                "backgroundFxQuery": "",
                "appMode": "auto"
              },
              "showViewerNavigation": true,
              "homePageId": "4726e34e-2599-4fc1-9172-b0c2bda7ce68",
              "appId": "62ee07c7-9d1e-4b9f-bb7b-ee1945dd45a9",
              "currentEnvironmentId": "50f55fc8-608e-4bbb-a79f-24306fe81e23",
              "promotedFrom": null,
              "createdAt": "2024-08-02T12:27:34.121Z",
              "updatedAt": "2024-08-02T12:27:34.111Z"
            }
          ],
          "appEnvironments": [
            {
              "id": "50f55fc8-608e-4bbb-a79f-24306fe81e23",
              "organizationId": "ad9fffc1-fdd6-4036-be86-ea745954f560",
              "name": "development",
              "isDefault": false,
              "priority": 1,
              "enabled": true,
              "createdAt": "2024-08-02T10:39:46.915Z",
              "updatedAt": "2024-08-02T10:39:46.915Z"
            },
            {
              "id": "d6a65d8e-b2ed-44c2-9985-9dcf5a856fac",
              "organizationId": "ad9fffc1-fdd6-4036-be86-ea745954f560",
              "name": "staging",
              "isDefault": false,
              "priority": 2,
              "enabled": true,
              "createdAt": "2024-08-02T10:39:46.915Z",
              "updatedAt": "2024-08-02T10:39:46.915Z"
            },
            {
              "id": "27d7419e-9673-4653-bfd9-c3675d48998f",
              "organizationId": "ad9fffc1-fdd6-4036-be86-ea745954f560",
              "name": "production",
              "isDefault": true,
              "priority": 3,
              "enabled": true,
              "createdAt": "2024-08-02T10:39:46.915Z",
              "updatedAt": "2024-08-02T10:39:46.915Z"
            }
          ],
          "dataSourceOptions": [],
          "schemaDetails": {
            "multiPages": true,
            "multiEnv": true,
            "globalDataSources": true
          }
        }
      }
    }
  ],
  "tooljet_version": "2.62.0-ee2.21.0"
}