{
  "tooljet_database": [],
  "app": [
    {
      "definition": {
        "appV2": {
          "id": "4a3abb1b-61f2-41f0-8f64-ca1a7f91e130",
          "type": "front-end",
          "name": "Hammes-template-app",
          "slug": "4a3abb1b-61f2-41f0-8f64-ca1a7f91e130",
          "isPublic": null,
          "isMaintenanceOn": false,
          "icon": "menuhome",
          "organizationId": "c453b5eb-e22f-40ec-adb0-8bb1f308686a",
          "currentVersionId": null,
          "userId": "3f5982f2-9b56-4112-8353-33bac6bfa909",
          "workflowApiToken": null,
          "workflowEnabled": false,
          "createdAt": "2024-07-02T07:36:16.001Z",
          "creationMode": "DEFAULT",
          "updatedAt": "2024-07-02T07:36:16.000Z",
          "editingVersion": {
            "id": "5cc16135-5b4a-446a-9333-a428e67a458d",
            "name": "v1",
            "definition": null,
            "globalSettings": {
              "hideHeader": false,
              "appInMaintenance": false,
              "canvasMaxWidth": 100,
              "canvasMaxWidthType": "%",
              "canvasMaxHeight": 2400,
              "canvasBackgroundColor": "#edeff5",
              "backgroundFxQuery": "",
              "appMode": "auto"
            },
            "showViewerNavigation": true,
            "homePageId": "f08c0da6-dd92-4a15-a087-ddac5fcd4979",
            "appId": "4a3abb1b-61f2-41f0-8f64-ca1a7f91e130",
            "currentEnvironmentId": "a8165c68-9485-4987-a07c-e445dd91c131",
            "promotedFrom": null,
            "createdAt": "2024-07-02T07:36:16.126Z",
            "updatedAt": "2024-07-02T07:36:21.039Z"
          },
          "components": [
            {
              "id": "9b5c14fa-6be2-47f5-b1af-4a24c4332ad0",
              "name": "deshawn",
              "type": "TextInput",
              "pageId": "f08c0da6-dd92-4a15-a087-ddac5fcd4979",
              "parent": null,
              "properties": {},
              "general": null,
              "styles": {},
              "generalStyles": null,
              "displayPreferences": {
                "showOnDesktop": {
                  "value": "{{true}}"
                },
                "showOnMobile": {
                  "value": "{{false}}"
                }
              },
              "validation": {},
              "createdAt": "2024-07-02T07:36:20.118Z",
              "updatedAt": "2024-07-02T07:36:21.037Z",
              "layouts": [
                {
                  "id": "9746e20b-c16e-4c78-84c8-8f0b7101858f",
                  "type": "desktop",
                  "top": 240,
                  "left": 10,
                  "width": 10,
                  "height": 40,
                  "componentId": "9b5c14fa-6be2-47f5-b1af-4a24c4332ad0",
                  "dimensionUnit": "count",
                  "updatedAt": "2024-07-02T07:36:20.118Z"
                },
                {
                  "id": "97f53f35-05f2-489c-b959-7bcf7830efe6",
                  "type": "mobile",
                  "top": 240,
                  "left": 10,
                  "width": 10,
                  "height": 40,
                  "componentId": "9b5c14fa-6be2-47f5-b1af-4a24c4332ad0",
                  "dimensionUnit": "count",
                  "updatedAt": "2024-07-02T07:36:20.118Z"
                }
              ]
            }
          ],
          "pages": [
            {
              "id": "f08c0da6-dd92-4a15-a087-ddac5fcd4979",
              "name": "Home",
              "handle": "home",
              "index": 1,
              "disabled": null,
              "hidden": null,
              "createdAt": "2024-07-02T07:36:16.000Z",
              "updatedAt": "2024-07-02T07:36:16.000Z",
              "autoComputeLayout": true,
              "appVersionId": "5cc16135-5b4a-446a-9333-a428e67a458d"
            }
          ],
          "events": [],
          "dataQueries": [],
          "dataSources": [],
          "appVersions": [
            {
              "id": "5cc16135-5b4a-446a-9333-a428e67a458d",
              "name": "v1",
              "definition": null,
              "globalSettings": {
                "hideHeader": false,
                "appInMaintenance": false,
                "canvasMaxWidth": 100,
                "canvasMaxWidthType": "%",
                "canvasMaxHeight": 2400,
                "canvasBackgroundColor": "#edeff5",
                "backgroundFxQuery": "",
                "appMode": "auto"
              },
              "showViewerNavigation": true,
              "homePageId": "f08c0da6-dd92-4a15-a087-ddac5fcd4979",
              "appId": "4a3abb1b-61f2-41f0-8f64-ca1a7f91e130",
              "currentEnvironmentId": "a8165c68-9485-4987-a07c-e445dd91c131",
              "promotedFrom": null,
              "createdAt": "2024-07-02T07:36:16.126Z",
              "updatedAt": "2024-07-02T07:36:21.039Z"
            }
          ],
          "appEnvironments": [
            {
              "id": "a8165c68-9485-4987-a07c-e445dd91c131",
              "organizationId": "c453b5eb-e22f-40ec-adb0-8bb1f308686a",
              "name": "development",
              "isDefault": false,
              "priority": 1,
              "enabled": true,
              "createdAt": "2024-07-02T06:50:24.803Z",
              "updatedAt": "2024-07-02T06:50:24.803Z"
            },
            {
              "id": "7e947ad7-cfcb-4aa8-9156-b8b43745820e",
              "organizationId": "c453b5eb-e22f-40ec-adb0-8bb1f308686a",
              "name": "staging",
              "isDefault": false,
              "priority": 2,
              "enabled": true,
              "createdAt": "2024-07-02T06:50:24.803Z",
              "updatedAt": "2024-07-02T06:50:24.803Z"
            },
            {
              "id": "d87039ac-7881-46f9-9653-c1a5d9848393",
              "organizationId": "c453b5eb-e22f-40ec-adb0-8bb1f308686a",
              "name": "production",
              "isDefault": true,
              "priority": 3,
              "enabled": true,
              "createdAt": "2024-07-02T06:50:24.803Z",
              "updatedAt": "2024-07-02T06:50:24.803Z"
            }
          ],
          "dataSourceOptions": [],
          "schemaDetails": {
            "multiPages": true,
            "multiEnv": true,
            "globalDataSources": true
          }
        }
      }
    }
  ],
  "tooljet_version": "2.62.0-ee2.20.0"
}