{
  "tooljet_database": [],
  "app": [
    {
      "definition": {
        "appV2": {
          "id": "c6b1de03-1e01-4442-bc7f-3e59d6b11147",
          "type": "front-end",
          "name": "Hilll-template-app",
          "slug": "c6b1de03-1e01-4442-bc7f-3e59d6b11147",
          "isPublic": null,
          "isMaintenanceOn": false,
          "icon": "folderupload",
          "organizationId": "4539b32f-9150-4bee-a1eb-832b31ef9971",
          "currentVersionId": null,
          "userId": "795ef970-ec3f-42da-9cd9-06d68e45d49b",
          "workflowApiToken": null,
          "workflowEnabled": false,
          "createdAt": "2024-06-26T06:27:42.564Z",
          "creationMode": "DEFAULT",
          "updatedAt": "2024-06-26T06:27:42.564Z",
          "editingVersion": {
            "id": "c80ce1a5-bd14-49b1-a4cf-55e817b046dc",
            "name": "v2",
            "definition": null,
            "globalSettings": {
              "hideHeader": false,
              "appInMaintenance": false,
              "canvasMaxWidth": 100,
              "canvasMaxWidthType": "%",
              "canvasMaxHeight": 2400,
              "canvasBackgroundColor": "#edeff5",
              "backgroundFxQuery": "",
              "appMode": "auto"
            },
            "showViewerNavigation": true,
            "homePageId": "ebd395ec-4a10-481c-b9cc-eb472891b275",
            "appId": "c6b1de03-1e01-4442-bc7f-3e59d6b11147",
            "currentEnvironmentId": "d3e89c10-1e7e-4cc7-9573-06925674ddc6",
            "promotedFrom": null,
            "createdAt": "2024-06-26T06:27:52.749Z",
            "updatedAt": "2024-06-26T06:27:52.490Z"
          },
          "components": [
            {
              "id": "7c1c666c-4e83-4c5c-9a47-442f11c75936",
              "name": "minnie",
              "type": "TextInput",
              "pageId": "ebd395ec-4a10-481c-b9cc-eb472891b275",
              "parent": null,
              "properties": {},
              "general": null,
              "styles": {},
              "generalStyles": null,
              "displayPreferences": {
                "showOnDesktop": {
                  "value": "{{true}}"
                },
                "showOnMobile": {
                  "value": "{{false}}"
                }
              },
              "validation": {},
              "createdAt": "2024-06-26T06:27:52.490Z",
              "updatedAt": "2024-06-26T06:27:52.490Z",
              "layouts": [
                {
                  "id": "65afce9e-7fa7-4e14-a1b4-430c76edc5a5",
                  "type": "desktop",
                  "top": 240,
                  "left": 10,
                  "width": 10,
                  "height": 40,
                  "componentId": "7c1c666c-4e83-4c5c-9a47-442f11c75936",
                  "dimensionUnit": "count",
                  "updatedAt": "2024-06-26T06:27:52.490Z"
                },
                {
                  "id": "b447a685-638c-473e-aa89-1d21c3162d3e",
                  "type": "mobile",
                  "top": 240,
                  "left": 10,
                  "width": 10,
                  "height": 40,
                  "componentId": "7c1c666c-4e83-4c5c-9a47-442f11c75936",
                  "dimensionUnit": "count",
                  "updatedAt": "2024-06-26T06:27:52.490Z"
                }
              ]
            }
          ],
          "pages": [
            {
              "id": "ebd395ec-4a10-481c-b9cc-eb472891b275",
              "name": "Home",
              "handle": "home",
              "index": 1,
              "disabled": null,
              "hidden": null,
              "createdAt": "2024-06-26T06:27:52.490Z",
              "updatedAt": "2024-06-26T06:27:52.490Z",
              "autoComputeLayout": false,
              "appVersionId": "c80ce1a5-bd14-49b1-a4cf-55e817b046dc"
            }
          ],
          "events": [],
          "dataQueries": [],
          "dataSources": [],
          "appVersions": [
            {
              "id": "c80ce1a5-bd14-49b1-a4cf-55e817b046dc",
              "name": "v2",
              "definition": null,
              "globalSettings": {
                "hideHeader": false,
                "appInMaintenance": false,
                "canvasMaxWidth": 100,
                "canvasMaxWidthType": "%",
                "canvasMaxHeight": 2400,
                "canvasBackgroundColor": "#edeff5",
                "backgroundFxQuery": "",
                "appMode": "auto"
              },
              "showViewerNavigation": true,
              "homePageId": "ebd395ec-4a10-481c-b9cc-eb472891b275",
              "appId": "c6b1de03-1e01-4442-bc7f-3e59d6b11147",
              "currentEnvironmentId": "d3e89c10-1e7e-4cc7-9573-06925674ddc6",
              "promotedFrom": null,
              "createdAt": "2024-06-26T06:27:52.749Z",
              "updatedAt": "2024-06-26T06:27:52.490Z"
            }
          ],
          "appEnvironments": [
            {
              "id": "d3e89c10-1e7e-4cc7-9573-06925674ddc6",
              "organizationId": "4539b32f-9150-4bee-a1eb-832b31ef9971",
              "name": "development",
              "isDefault": false,
              "priority": 1,
              "enabled": true,
              "createdAt": "2024-06-26T05:55:00.533Z",
              "updatedAt": "2024-06-26T05:55:00.533Z"
            },
            {
              "id": "f98bc9db-f791-4a4a-a65b-174406a8a7d9",
              "organizationId": "4539b32f-9150-4bee-a1eb-832b31ef9971",
              "name": "staging",
              "isDefault": false,
              "priority": 2,
              "enabled": true,
              "createdAt": "2024-06-26T05:55:00.533Z",
              "updatedAt": "2024-06-26T05:55:00.533Z"
            },
            {
              "id": "ce1fb78f-23da-44c0-8437-d3873db15f36",
              "organizationId": "4539b32f-9150-4bee-a1eb-832b31ef9971",
              "name": "production",
              "isDefault": true,
              "priority": 3,
              "enabled": true,
              "createdAt": "2024-06-26T05:55:00.533Z",
              "updatedAt": "2024-06-26T05:55:00.533Z"
            }
          ],
          "dataSourceOptions": [],
          "schemaDetails": {
            "multiPages": true,
            "multiEnv": true,
            "globalDataSources": true
          }
        }
      }
    }
  ],
  "tooljet_version": "2.61.0-ee2.20.0"
}