{
  "tooljet_database": [],
  "app": [
    {
      "definition": {
        "appV2": {
          "id": "6081feef-496d-41b4-880f-5328213e8e9b",
          "type": "front-end",
          "name": "Hudson-template-app",
          "slug": "6081feef-496d-41b4-880f-5328213e8e9b",
          "isPublic": null,
          "isMaintenanceOn": false,
          "icon": "draghandle",
          "organizationId": "f4328b35-05d1-4687-a6df-36c61c90733e",
          "currentVersionId": null,
          "userId": "4a2d3b4d-146b-4694-9185-631bde2e1ae8",
          "workflowApiToken": null,
          "workflowEnabled": false,
          "createdAt": "2024-02-28T13:49:05.087Z",
          "creationMode": "DEFAULT",
          "updatedAt": "2024-02-28T13:49:05.087Z",
          "editingVersion": {
            "id": "91a49848-ca6f-4dc5-8cac-821bf7c896d1",
            "name": "v1",
            "definition": null,
            "globalSettings": {
              "hideHeader": false,
              "appInMaintenance": false,
              "canvasMaxWidth": 100,
              "canvasMaxWidthType": "%",
              "canvasMaxHeight": 2400,
              "canvasBackgroundColor": "#edeff5",
              "backgroundFxQuery": ""
            },
            "showViewerNavigation": true,
            "homePageId": "57e0be57-ff68-44d6-a78b-62a74fcfa0cc",
            "appId": "6081feef-496d-41b4-880f-5328213e8e9b",
            "currentEnvironmentId": "18c7f20b-64ba-4c08-a080-980baca48f38",
            "promotedFrom": null,
            "createdAt": "2024-02-28T13:49:05.113Z",
            "updatedAt": "2024-02-28T13:49:09.964Z"
          },
          "components": [
            {
              "id": "131239d7-588c-4a83-857b-0f0b1ac245e0",
              "name": "andreanne",
              "type": "Text",
              "pageId": "57e0be57-ff68-44d6-a78b-62a74fcfa0cc",
              "parent": null,
              "properties": {},
              "general": null,
              "styles": {},
              "generalStyles": null,
              "displayPreferences": {
                "showOnDesktop": {
                  "value": "{{true}}"
                },
                "showOnMobile": {
                  "value": "{{false}}"
                }
              },
              "validation": {},
              "createdAt": "2024-02-28T13:49:08.979Z",
              "updatedAt": "2024-02-28T13:49:09.948Z",
              "layouts": [
                {
                  "id": "3138ce32-1ab3-4edc-8970-7a0638fab860",
                  "type": "desktop",
                  "top": 240,
                  "left": 23.25581395348837,
                  "width": 6,
                  "height": 40,
                  "componentId": "131239d7-588c-4a83-857b-0f0b1ac245e0"
                },
                {
                  "id": "73d6d92f-4423-42a1-a3c1-bdbcb81027df",
                  "type": "mobile",
                  "top": 240,
                  "left": 23.25581395348837,
                  "width": 6,
                  "height": 40,
                  "componentId": "131239d7-588c-4a83-857b-0f0b1ac245e0"
                }
              ]
            }
          ],
          "pages": [
            {
              "id": "57e0be57-ff68-44d6-a78b-62a74fcfa0cc",
              "name": "Home",
              "handle": "home",
              "index": 1,
              "disabled": null,
              "hidden": null,
              "createdAt": "2024-02-28T13:49:05.087Z",
              "updatedAt": "2024-02-28T13:49:05.087Z",
              "appVersionId": "91a49848-ca6f-4dc5-8cac-821bf7c896d1"
            }
          ],
          "events": [],
          "dataQueries": [],
          "dataSources": [],
          "appVersions": [
            {
              "id": "91a49848-ca6f-4dc5-8cac-821bf7c896d1",
              "name": "v1",
              "definition": null,
              "globalSettings": {
                "hideHeader": false,
                "appInMaintenance": false,
                "canvasMaxWidth": 100,
                "canvasMaxWidthType": "%",
                "canvasMaxHeight": 2400,
                "canvasBackgroundColor": "#edeff5",
                "backgroundFxQuery": ""
              },
              "showViewerNavigation": true,
              "homePageId": "57e0be57-ff68-44d6-a78b-62a74fcfa0cc",
              "appId": "6081feef-496d-41b4-880f-5328213e8e9b",
              "currentEnvironmentId": "18c7f20b-64ba-4c08-a080-980baca48f38",
              "promotedFrom": null,
              "createdAt": "2024-02-28T13:49:05.113Z",
              "updatedAt": "2024-02-28T13:49:09.964Z"
            }
          ],
          "appEnvironments": [
            {
              "id": "18c7f20b-64ba-4c08-a080-980baca48f38",
              "organizationId": "f4328b35-05d1-4687-a6df-36c61c90733e",
              "name": "development",
              "isDefault": false,
              "priority": 1,
              "enabled": true,
              "createdAt": "2024-02-28T13:24:14.194Z",
              "updatedAt": "2024-02-28T13:24:14.194Z"
            },
            {
              "id": "8e617989-b041-4c00-9877-f48c81d4d427",
              "organizationId": "f4328b35-05d1-4687-a6df-36c61c90733e",
              "name": "staging",
              "isDefault": false,
              "priority": 2,
              "enabled": true,
              "createdAt": "2024-02-28T13:24:14.194Z",
              "updatedAt": "2024-02-28T13:24:14.194Z"
            },
            {
              "id": "ff0043ef-e139-4c6a-8929-477eb98cefdb",
              "organizationId": "f4328b35-05d1-4687-a6df-36c61c90733e",
              "name": "production",
              "isDefault": true,
              "priority": 3,
              "enabled": true,
              "createdAt": "2024-02-28T13:24:14.194Z",
              "updatedAt": "2024-02-28T13:24:14.194Z"
            }
          ],
          "dataSourceOptions": [],
          "schemaDetails": {
            "multiPages": true,
            "multiEnv": true,
            "globalDataSources": true
          }
        }
      }
    }
  ],
  "tooljet_version": "2.30.3-ee2.15.6"
}